{
    "_links": {
        "self": {
            "href": "http:\/\/default\/admin\/structure\/menu\/item\/9\/edit?_format=hal_json"
        },
        "type": {
            "href": "http:\/\/drupal.org\/rest\/type\/menu_link_content\/menu_link_content"
        }
    },
    "uuid": [
        {
            "value": "8f6c0498-9766-4f80-8247-718a3f2c9fe7"
        }
    ],
    "bundle": [
        {
            "value": "menu_link_content"
        }
    ],
    "title": [
        {
            "value": "Membership",
            "lang": "en"
        }
    ],
    "menu_name": [
        {
            "value": "top-menu"
        }
    ],
    "link": [
        {
            "uri": "internal:\/",
            "title": "",
            "options": []
        }
    ],
    "external": [
        {
            "value": "0"
        }
    ],
    "rediscover": [
        {
            "value": "1"
        }
    ],
    "weight": [
        {
            "value": "-49"
        }
    ],
    "expanded": [
        {
            "value": "0"
        }
    ],
    "enabled": [
        {
            "value": "1"
        }
    ],
    "langcode": [
        {
            "value": "en",
            "lang": "en"
        }
    ],
    "changed": [
        {
            "value": "1445526397",
            "lang": "en"
        }
    ],
    "default_langcode": [
        {
            "value": "1",
            "lang": "en"
        }
    ]
}